{
  "generator-jhipster": {
    "applicationType": "microservice",
    "authenticationType": "jwt",
    "baseName": "TheWhisperingBook",
    "buildTool": "gradle",
    "cacheProvider": "redis",
    "clientFramework": "react",
    "clientTestFrameworks": [],
    "clientTheme": "sketchy",
    "clientThemeVariant": "primary",
    "creationTimestamp": 1731154989289,
    "databaseType": "mongodb",
    "devDatabaseType": null,
    "devServerPort": 9060,
    "enableGradleEnterprise": false,
    "enableHibernateCache": null,
    "enableSwaggerCodegen": false,
    "enableTranslation": true,
    "entities": [],
    "feignClient": false,
    "gradleEnterpriseHost": null,
    "jhipsterVersion": "8.7.3",
    "jwtSecretKey": "ZDRhNThkNTFhY2MyOTJmOGM2MWJkNmFjZTE4Y2E2ZjYyNzhlNWEwNzFmNzg1YjZjM2U4NjUyNDQ1YzA0YTMxNTIxNzZmNjJkNDVmM2YyYTMyYzk0ODYzMWUyY2RlZjQ5Yzk2Yjk3NTcwMzA3YTBiNjc3MmM4ODY1ZWZlNmQ2NTA=",
    "languages": ["en"],
    "messageBroker": false,
    "microfrontend": null,
    "microfrontends": [],
    "nativeLanguage": "en",
    "packageName": "com.thewhisperingbook",
    "prodDatabaseType": null,
    "reactive": false,
    "searchEngine": false,
    "serverPort": 8081,
    "serverSideOptions": [],
    "serviceDiscoveryType": "consul",
    "syncUserWithIdp": null,
    "testFrameworks": [],
    "websocket": false,
    "withAdminUi": true
  }
}
